{
  "about": {
    "widgets": [
      {
        "title": "Who Am I...",
        "description": "I am this guys thats a dude"
      },
      {
        "title": "But I also do...",
        "description": "I also do some other things too..."
      }
    ],
    "info": [
      {
        "title": "I have...",
        "items": [
          {
            "title": "6 Years",
            "subTitle": "Done 6 years of programming"
          },
          {
            "title": "2 Hacks",
            "subTitle": "Helped organize 2 Hackathons"
          },
          {
            "title": "2 Years",
            "subTitle": "Worked 2 years professionally"
          },
          {
            "title": "15 Langs",
            "subTitle": "Have programmed in 15 different Languages"
          }
        ]
      },
      {
        "title": "But I also have...",
        "items": [
          {
            "image": "/svgs/about/have/bike.svg",
            "subTitle": "Biked 140KM in one day"
          },
          {
            "image": "/svgs/about/have/mountain.svg",
            "subTitle": "Concurred the Sleeping Giant"
          },
          {
            "image": "/svgs/about/have/nesting-doll.svg",
            "subTitle": "Been attempting to learn Russian "
          },
          {
            "image": "/svgs/about/have/vr-headset.svg",
            "subTitle": "A passion for VR and Physical computing"
          }
        ]
      },
      {
        "title": "Right now I am working on...",
        "items": [
          {
            "image": "/svgs/about/currently/hackville.svg",
            "bigImage": true,
            "title": "Hackville 2021",
            "link": "https://www.hackville.club",
            "subTitle": "Student run virtual hackathon"
          },
          {
            "image": "/svgs/about/currently/wasmcompute.svg",
            "bigImage": true,
            "title": "WASM Compute",
            "link": "https://wasmcompute.com",
            "subTitle": "Experimental Serverless Platform for Web Assembly"
          },
          {
            "bigImage": true,
            "image": "/svgs/about/currently/thesis.svg",
            "title": "Thesis",
            "subTitle": "A thesis reviewing stateful serverless platforms"
          }
        ]
      }
    ],
    "favoriteLang": {
      "title": "My favorite programming languages are ...",
      "items": [
        {
          "bigImage": true,
          "image": "/svgs/about/programming/rust.svg",
          "subTitle": "Rust is love, Rust is life"
        },
        {
          "bigImage": true,
          "image": "/svgs/about/programming/typescript.svg",
          "subTitle": "Typescript cause its easy and fun"
        },
        {
          "bigImage": true,
          "image": "/svgs/about/programming/go.svg",
          "subTitle": "GoLang for a life simple"
        },
        {
          "bigImage": true,
          "image": "/svgs/about/programming/python.svg",
          "subTitle": "Python for machine learning and stuff"
        }
      ]
    },
    "interested": {
      "title": "And I'm personally interested in ...",
      "items": [
        {
          "bigImage": true,
          "image": "/svgs/about/interests/systems.svg",
          "subTitle": "Distributed Systems"
        },
        {
          "bigImage": true,
          "image": "/svgs/about/interests/wasm.svg",
          "subTitle": "Web Assembly"
        },
        {
          "bigImage": true,
          "image": "/svgs/about/interests/cloud.svg",
          "subTitle": "The Cloud"
        }
      ]
    }
  }
}